xblock/__init__.py
xblock/completable.py
xblock/core.py
xblock/exceptions.py
xblock/field_data.py
xblock/fields.py
xblock/fragment.py
xblock/internal.py
xblock/plugin.py
xblock/progress.py
xblock/run_script.py
xblock/runtime.py
xblock/scorable.py
xblock/validation.py
xblock/django/__init__.py
xblock/django/request.py
xblock/reference/__init__.py
xblock/reference/plugins.py
xblock/reference/user_service.py
xblock/test/__init__.py
xblock/test/settings.py
xblock/test/test_asides.py
xblock/test/test_completable.py
xblock/test/test_core.py
xblock/test/test_core_capabilities.py
xblock/test/test_field_data.py
xblock/test/test_fields.py
xblock/test/test_fields_api.py
xblock/test/test_fragment.py
xblock/test/test_internal.py
xblock/test/test_json_conversion.py
xblock/test/test_parsing.py
xblock/test/test_plugin.py
xblock/test/test_progress.py
xblock/test/test_runtime.py
xblock/test/test_scorable.py
xblock/test/test_test_tools.py
xblock/test/test_user_service.py
xblock/test/test_validation.py
xblock/test/tools.py
xblock/test/toy_runtime.py
xblock/test/django/__init__.py
xblock/test/django/test_field_translation.py
xblock/test/django/test_request.py
xblock/test/locale/de/LC_MESSAGES/django.mo
xblock/test/locale/de/LC_MESSAGES/django.po
xblock/test/utils/__init__.py
xblock/test/utils/test_helpers.py
xblock/test/utils/test_publish_event.py
xblock/test/utils/test_resources.py
xblock/test/utils/test_settings.py
xblock/test/utils/data/__init__.py
xblock/test/utils/data/another_template.xml
xblock/test/utils/data/l10n_django_template.txt
xblock/test/utils/data/simple_django_template.txt
xblock/test/utils/data/simple_mako_template.txt
xblock/test/utils/data/simple_template.xml
xblock/test/utils/data/trans_django_template.txt
xblock/test/utils/data/translations/eo/LC_MESSAGES/text.mo
xblock/test/utils/data/translations/eo/LC_MESSAGES/text.po
xblock/utils/__init__.py
xblock/utils/helpers.py
xblock/utils/publish_event.py
xblock/utils/resources.py
xblock/utils/settings.py
xblock-5.3.0.dist-info/licenses/AUTHORS
xblock-5.3.0.dist-info/licenses/LICENSE.TXT
xblock-5.3.0.dist-info/licenses/NOTICE.txt
xblock-5.3.0.dist-info/METADATA
xblock-5.3.0.dist-info/WHEEL
xblock-5.3.0.dist-info/top_level.txt
xblock-5.3.0.dist-info/RECORD
